{"type":"FeatureCollection","crs":{"type":"name","properties":{"name":"EPSG:4326"}},"features":[{"type":"Feature","id":0,"geometry":{"type":"Point","coordinates":[-76.328862396999966,-6.92616805199998]},"properties":{"FID":0,"N°":504,"CUI":"2530505","FECHA":1759190400000,"JERARQUIA":"RVD","COD_RUTA":"SM-107","RUTA_RECLA":"-","IDDPTO":"22","IDPROV":"2207","DPTO":"SAN MARTIN","PROV":"PICOTA","NOM_PUENTE":"PICOTA","HITO_KM":"0+977","LONGITUD_m":263,"CLASE":"DEFINITIVO","CONDICION":"REGULAR","N_CARRILES":2,"A_CALZADA":7.2000000000000002,"N_CONVENIO":"116-2024-MTC/21","INVENTARIO":"-","ZONA_UTM":"18S","FUENTE":"GO","CARTERA":"PROGRAMATICA","COMENTARIO":"-","A_F_A_PCTJ":"4.99 %","CUI_":2530505,"CUI_12":2530505,"NOMBRE_COR":"RENOVACION DE PUENTE PICOTA","COSTO":107212866.8,"NOMBRE_LAR":"RENOVACION DE PUENTE; EN EL(LA) CARRETERA EMP. PE-5N (PICOTA) - TINGO DE PONASA - SHAMBOYACU,  DISTRITO DE PICOTA, PROVINCIA PICOTA, DEPARTAMENTO SAN MARTIN","PMI":"PMI DEL SECTOR","PMI_AACTUA":31557192}}]}